trc/__init__.py
trc/_c_tools.py
trc/_filetools.py
trc/_functools.py
trc/_mathtools.py
trc/_systemtools.py
trc/_utils.py
trc/_vartools.py
trc/agent/__init__.py
trc/agent/_ask_user.py
trc/agent/_file_editor.py
trc/agent/_image_analyzer.py
trc/agent/_model.py
trc/agent/_parser.py
trc/agent/_proccessor.py
trc/agent/_shell.py
trc/agent/_wiki.py
trc/data/__init__.py
trc/data/_augmentation.py
trc/data/_hdf5.py
trc/data/_imagetools.py
trc/sets/_10x14.py
trc/sets/_5x8.py
trc/sets/__init__.py
trc-1.3.dist-info/METADATA
trc-1.3.dist-info/WHEEL
trc-1.3.dist-info/top_level.txt
trc-1.3.dist-info/RECORD
