Metadata-Version: 2.4
Name: trc
Version: 1.3
Summary: TRC (Total Resource Control) is a comprehensive Python package for enhancing Python's capabilities with utility functions. It offers robust tools for data operations (manipulation, augmentation, processing), specialized functionalities for character sets/patterns, and an innovative agent-based framework to streamline complex workflows and automate tasks, making code more concise, readable, and efficient across various development stages.
Author: TRC-Team
License: MIT
Requires-Dist: requests
Requires-Dist: pillow
Requires-Dist: psutil
Requires-Dist: h5py
Requires-Dist: ollama
Requires-Dist: google.generativeai
Requires-Dist: wikipedia
Dynamic: author
Dynamic: description
Dynamic: description-content-type
Dynamic: license
Dynamic: requires-dist
Dynamic: summary
